video_streaming/__init__.py
video_streaming/runner.py
video_streaming/processing/__init__.py
video_streaming/processing/datasets.py
video_streaming/processing/manager.py
video_streaming/processing/strategy.py
video_streaming/processing/stream.py
video_streaming/processing/writer.py
video_streaming_api-0.1.0.dist-info/LICENSE
video_streaming_api-0.1.0.dist-info/METADATA
video_streaming_api-0.1.0.dist-info/WHEEL
video_streaming_api-0.1.0.dist-info/top_level.txt
video_streaming_api-0.1.0.dist-info/RECORD
