Metadata-Version: 2.1
Name: video-streaming-api
Version: 0.1.0
Summary: process video streaming
Home-page: https://github.com/marcovwu/video-streaming-api
Author: MarcoWu
Author-email: marcowu1999@gmail.com
Project-URL: Source Code, https://github.com/marcovwu/video-streaming-api
Project-URL: Issue Tracker, https://github.com/marcovwu/video-streaming-api/issues
Classifier: Development Status :: 3 - Alpha
Classifier: Intended Audience :: Developers
Classifier: Topic :: Multimedia :: Video
Classifier: License :: OSI Approved :: MIT License
Classifier: Programming Language :: Python :: 3
Classifier: Programming Language :: Python :: 3.7
Classifier: Programming Language :: Python :: 3.8
Classifier: Programming Language :: Python :: 3.9
Classifier: Programming Language :: Python :: 3.10
Classifier: Operating System :: OS Independent
Requires-Python: >=3.7
License-File: LICENSE
Requires-Dist: tqdm
Requires-Dist: loguru
Requires-Dist: opencv-python
